aiogram_telemetry/__init__.py
aiogram_telemetry/config.py
aiogram_telemetry/setup.py
aiogram_telemetry/core/__init__.py
aiogram_telemetry/core/metrics.py
aiogram_telemetry/core/middleware.py
aiogram_telemetry/core/tracker.py
aiogram_telemetry/core/writer.py
aiogram_telemetry/exporter/__init__.py
aiogram_telemetry/exporter/prometheus.py
aiogram_telemetry/storage/__init__.py
aiogram_telemetry/storage/models.py
aiogram_telemetry/storage/postgres.py
aiogram_telemetry/storage/redis_store.py
aiogram_telemetry/utils/__init__.py
aiogram_telemetry/utils/clocks.py
aiogram_telemetry/utils/labels.py
aiogram_telemetry/utils/logging.py
aiogram_telemetry/utils/privacy.py
aiogram_telemetry-0.2.3.dist-info/licenses/LICENSE
aiogram_telemetry-0.2.3.dist-info/METADATA
aiogram_telemetry-0.2.3.dist-info/WHEEL
aiogram_telemetry-0.2.3.dist-info/top_level.txt
aiogram_telemetry-0.2.3.dist-info/RECORD
