Metadata-Version: 2.4
Name: aiogram-telemetry
Version: 0.2.3
Summary: Telemetry and observability helpers for aiogram 3 bots.
Author: aiogram-telemetry maintainers
License: MIT
Project-URL: Homepage, https://github.com/example/aiogram-telemetry
Project-URL: Documentation, https://github.com/example/aiogram-telemetry/docs
Keywords: aiogram,telemetry,prometheus,redis,observability
Classifier: Programming Language :: Python :: 3
Classifier: Programming Language :: Python :: 3 :: Only
Classifier: License :: OSI Approved :: MIT License
Classifier: Framework :: AsyncIO
Requires-Python: >=3.10
License-File: LICENSE
Requires-Dist: aiogram>=3
Requires-Dist: redis>=5
Requires-Dist: prometheus-client>=0.20
Requires-Dist: pydantic-settings>=2
Requires-Dist: aiohttp>=3
Provides-Extra: postgres
Requires-Dist: SQLAlchemy>=2; extra == "postgres"
Requires-Dist: asyncpg>=0.29; extra == "postgres"
Dynamic: license-file
